{"trial_id": "08", "hyperparameters": {"space": [{"class_name": "Int", "config": {"name": "units", "default": null, "conditions": [], "min_value": 32, "max_value": 512, "step": 32, "sampling": "linear"}}, {"class_name": "Choice", "config": {"name": "learning_rate", "default": 0.1, "conditions": [], "values": [0.1, 0.01, 0.001], "ordered": true}}, {"class_name": "Choice", "config": {"name": "activation", "default": "relu", "conditions": [], "values": ["relu", "sigmoid"], "ordered": false}}], "values": {"units": 320, "learning_rate": 0.001, "activation": "sigmoid"}}, "metrics": {"metrics": {"accuracy": {"direction": "max", "observations": [{"value": [0.8643866777420044], "step": 2}]}, "loss": {"direction": "min", "observations": [{"value": [0.45684516429901123], "step": 2}]}, "val_accuracy": {"direction": "max", "observations": [{"value": [0.8620399832725525], "step": 2}]}, "val_loss": {"direction": "min", "observations": [{"value": [0.46558627486228943], "step": 2}]}}}, "score": 0.8620399832725525, "best_step": 2, "status": "COMPLETED", "message": null}